README.rst
requirements.txt
setup.cfg
setup.py
python_kanbanize/__init__.py
python_kanbanize/credentials.py
python_kanbanize/wrapper.py
python_kanbanize.egg-info/PKG-INFO
python_kanbanize.egg-info/SOURCES.txt
python_kanbanize.egg-info/dependency_links.txt
python_kanbanize.egg-info/not-zip-safe
python_kanbanize.egg-info/requires.txt
python_kanbanize.egg-info/top_level.txt