Metadata-Version: 1.1
Name: python-kanbanize
Version: 0.2.0
Summary: Kanbanize.com Python API Wrapper
